markovnet
